[{"id":28907016,"name":"Illusionary Daytime","singer":"Shirfine","album":"Endless Daydream","image":"http://p1.music.126.net/8xNVCemkSNQptEyNw1PHKg==/8914840278033758.jpg","duration":250.723,"url":"https://music.163.com/song/media/outer/url?id=28907016.mp3"},{"id":483671599,"name":"追光者","singer":"岑宁儿","album":"夏至未至 影视原声带","image":"http://p2.music.126.net/ZZAQGWl9mR7g5xCyWWH3Pw==/19149094509535913.jpg","duration":235.833,"url":"https://music.163.com/song/media/outer/url?id=483671599.mp3"},{"id":1341964346,"name":"你的酒馆对我打了烊","singer":"陈雪凝","album":"你的酒馆对我打了烊","image":"http://p2.music.126.net/LiRR__0pJHSivqBHZzbMUw==/109951163816225567.jpg","duration":251.428,"url":"https://music.163.com/song/media/outer/url?id=1341964346.mp3"},{"id":31445772,"name":"理想三旬","singer":"陈鸿宇","album":"浓烟下的诗歌电台","image":"http://p1.music.126.net/cqTTEPAaxXG3cOwaE4E_-g==/109951163104103366.jpg","duration":210.814,"url":"https://music.163.com/song/media/outer/url?id=31445772.mp3"},{"id":514761281,"name":"白羊","singer":"徐秉龙/沈以诚","album":"白羊","image":"http://p1.music.126.net/tczb_7II9KzSuLQsVt89Gw==/109951163049336667.jpg","duration":168.42,"url":"https://music.163.com/song/media/outer/url?id=514761281.mp3"},{"id":29814898,"name":"可惜没如果","singer":"林俊杰","album":"新地球","image":"http://p1.music.126.net/X0EDfXzxMQJiQ-71JFGdZw==/3238061746556733.jpg","duration":298.276,"url":"https://music.163.com/song/media/outer/url?id=29814898.mp3"},{"id":39224884,"name":"Cheap Thrills","singer":"Sia","album":"This Is Acting","image":"http://p1.music.126.net/fDUMN_6ITc4gvoDko06uKw==/18176026719076230.jpg","duration":211.666,"url":"https://music.163.com/song/media/outer/url?id=39224884.mp3"},{"id":1345848098,"name":"绿色","singer":"陈雪凝","album":"绿色","image":"http://p2.music.126.net/R4ZP3AJ9xV0vvw8LX7AbMA==/109951163860425334.jpg","duration":269.59,"url":"https://music.163.com/song/media/outer/url?id=1345848098.mp3"},{"id":254574,"name":"后来","singer":"刘若英","album":"我等你","image":"http://p1.music.126.net/eBF7bHnJYBUfOFrJ_7SUfw==/109951163351825356.jpg","duration":341.4,"url":"https://music.163.com/song/media/outer/url?id=254574.mp3"},{"id":529668356,"name":"你要的全拿走","singer":"胡彦斌","album":"覅忒好","image":"http://p1.music.126.net/9uUWLnRsv4c0F0wu9dlttA==/109951163118372627.jpg","duration":299.333,"url":"https://music.163.com/song/media/outer/url?id=529668356.mp3"}]